Sorters-0.1.1.dist-info/METADATA
Sorters-0.1.1.dist-info/RECORD
Sorters-0.1.1.dist-info/WHEEL
Sorters-0.1.1.dist-info/top_level.txt
sorters/__init__.py
sorters/sorters.py
weekThreeDayFour/__init__.py
weekThreeDayFour/sorters.py
