Metadata-Version: 2.1
Name: Sorters
Version: 0.1.1
Summary: Sorter functions... for sorting.
Home-page: http://github.com/storborg/funniest
Author: Kimball
Author-email: flyingcircus@example.com
License: MIT
Platform: UNKNOWN
